testpypimkarakula/__init__.py
testpypimkarakula/m_mod_mkarakula.py
testpypimkarakula-0.0.1.dist-info/LICENSE.txt
testpypimkarakula-0.0.1.dist-info/METADATA
testpypimkarakula-0.0.1.dist-info/WHEEL
testpypimkarakula-0.0.1.dist-info/top_level.txt
testpypimkarakula-0.0.1.dist-info/RECORD
