Metadata-Version: 2.1
Name: testpypimkarakula
Version: 0.0.1
Summary: My test package
Author-email: michalkarakula007 <michalkarakula007@gmial.com>
License: MIT License
Keywords: testpypimkarakula,name
Classifier: Development Status :: 1 - Planning
Requires-Python: >=3.0
License-File: LICENSE.txt
Requires-Dist: numpy
